ps_typer/__init__.py
ps_typer/assets/InconsolataBold.ttf
ps_typer/assets/icon.png
ps_typer/assets/sounds/README.md
ps_typer/assets/sounds/key_1.wav
ps_typer/assets/sounds/key_2.wav
ps_typer/assets/sounds/key_3.wav
ps_typer/assets/sounds/key_4.wav
ps_typer/data/.gitignore
ps_typer/data/__init__.py
ps_typer/data/highscores_data_handler.py
ps_typer/data/style.py
ps_typer/data/texts/__init__.py
ps_typer/data/texts/brown.txt
ps_typer/data/texts/common_phrases.txt
ps_typer/data/texts/facts.txt
ps_typer/data/texts/famous_literature.txt
ps_typer/data/texts/famous_quotes.txt
ps_typer/data/texts/generate_texts.py
ps_typer/data/texts/gutenberg.txt
ps_typer/data/texts/webtext.txt
ps_typer/data/user_preferences_handler.py
ps_typer/data/utils.py
ps_typer/main.py
ps_typer/type_test/__init__.py
ps_typer/type_test/components/__init__.py
ps_typer/type_test/components/switch.py
ps_typer/type_test/main_menu.py
ps_typer/type_test/results.py
ps_typer/type_test/settings.py
ps_typer/type_test/statistics.py
ps_typer/type_test/texts.py
ps_typer/type_test/type_test.py
ps_typer/ui/__init__.py
ps_typer/ui/compile_ui_files.sh
ps_typer/ui/main_menu.py
ps_typer/ui/results_window.py
ps_typer/ui/settings_window.py
ps_typer/ui/source/main_menu.ui
ps_typer/ui/source/results_window.ui
ps_typer/ui/source/settings_window.ui
ps_typer/ui/source/stats_window.ui
ps_typer/ui/source/typing_window.ui
ps_typer/ui/stats_window.py
ps_typer/ui/typing_window.py
ps_typer-0.2.7.dist-info/entry_points.txt
ps_typer-0.2.7.dist-info/LICENSE
ps_typer-0.2.7.dist-info/WHEEL
ps_typer-0.2.7.dist-info/METADATA
ps_typer-0.2.7.dist-info/RECORD
