Metadata-Version: 2.1
Name: ps-typer
Version: 0.2.7
Summary: A Python program built on the PyQt5 GUI framework, used for practicing your typing skills and keeping track of your progress.
Home-page: https://github.com/Rolv-Apneseth/ps-typer
License: MIT
Author: Rolv-Apneseth
Author-email: rolv.apneseth@gmail.com
Requires-Python: >=3.9,<4.0.0
Classifier: License :: OSI Approved :: MIT License
Classifier: Programming Language :: Python :: 3
Classifier: Programming Language :: Python :: 3.10
Classifier: Programming Language :: Python :: 3.9
Requires-Dist: DateTime (>=4.4,<5.0)
Requires-Dist: PyQt5 (>=5.15.6,<6.0.0)
Requires-Dist: appdirs (>=1.4.4,<2.0.0)
Requires-Dist: dataclasses-json (>=0.5.7,<0.6.0)
Requires-Dist: pyqtgraph (>=0.12.4,<0.13.0)
